synkro/__init__.py
synkro/advanced.py
synkro/api.py
synkro/cli.py
synkro/errors.py
synkro/factory.py
synkro/ingestion.py
synkro/parsers.py
synkro/pipelines.py
synkro/reporting.py
synkro/schemas.py
synkro/session.py
synkro/tools.py
synkro/core/__init__.py
synkro/core/checkpoint.py
synkro/core/dataset.py
synkro/core/policy.py
synkro/coverage/__init__.py
synkro/coverage/calculator.py
synkro/coverage/improver.py
synkro/coverage/scenario_tagger.py
synkro/coverage/taxonomy_extractor.py
synkro/examples/__init__.py
synkro/formatters/__init__.py
synkro/formatters/bert.py
synkro/formatters/chatml.py
synkro/formatters/langfuse.py
synkro/formatters/langsmith.py
synkro/formatters/messages.py
synkro/formatters/qa.py
synkro/formatters/tool_call.py
synkro/generation/__init__.py
synkro/generation/follow_ups.py
synkro/generation/generator.py
synkro/generation/golden_responses.py
synkro/generation/golden_scenarios.py
synkro/generation/golden_tool_responses.py
synkro/generation/logic_extractor.py
synkro/generation/logic_extractor_fast.py
synkro/generation/multiturn_responses.py
synkro/generation/planner.py
synkro/generation/responses.py
synkro/generation/scenarios.py
synkro/generation/tool_responses.py
synkro/generation/tool_simulator.py
synkro/interactive/__init__.py
synkro/interactive/hitl_session.py
synkro/interactive/intent_classifier.py
synkro/interactive/live_display.py
synkro/interactive/logic_map_editor.py
synkro/interactive/rich_ui.py
synkro/interactive/scenario_editor.py
synkro/interactive/standalone.py
synkro/interactive/taxonomy_editor.py
synkro/llm/__init__.py
synkro/llm/client.py
synkro/llm/rate_limits.py
synkro/models/__init__.py
synkro/models/anthropic.py
synkro/models/cerebras.py
synkro/models/google.py
synkro/models/local.py
synkro/models/openai.py
synkro/modes/__init__.py
synkro/modes/config.py
synkro/modes/conversation.py
synkro/modes/tool_call.py
synkro/pipeline/__init__.py
synkro/pipeline/phases.py
synkro/pipeline/runner.py
synkro/prompts/__init__.py
synkro-0.5.31.dist-info/METADATA
synkro-0.5.31.dist-info/WHEEL
synkro-0.5.31.dist-info/entry_points.txt
synkro-0.5.31.dist-info/licenses/LICENSE
synkro-0.5.31.dist-info/RECORD
