Metadata-Version: 2.4
Name: synkro
Version: 0.5.31
Summary: Curate, evaluate, and ship LLM datasets from any document
Author: Murtaza Meerza
License-Expression: Apache-2.0
License-File: LICENSE
Keywords: dataset-generation,fine-tuning,llm,synthetic-data,training-data
Classifier: Development Status :: 4 - Beta
Classifier: Intended Audience :: Developers
Classifier: License :: OSI Approved :: Apache Software License
Classifier: Programming Language :: Python :: 3
Classifier: Programming Language :: Python :: 3.10
Classifier: Programming Language :: Python :: 3.11
Classifier: Programming Language :: Python :: 3.12
Classifier: Topic :: Scientific/Engineering :: Artificial Intelligence
Requires-Python: >=3.10
Requires-Dist: aiosqlite>=0.19
Requires-Dist: beautifulsoup4>=4.12
Requires-Dist: html2text>=2020.1
Requires-Dist: httpx>=0.25
Requires-Dist: litellm>=1.40
Requires-Dist: mammoth>=1.6
Requires-Dist: pydantic>=2.0
Requires-Dist: pymupdf>=1.24
Requires-Dist: readchar>=4.0
Requires-Dist: rich>=13.0
Requires-Dist: sqlalchemy[asyncio]>=2.0
Requires-Dist: typer>=0.9
Provides-Extra: dev
Requires-Dist: pre-commit>=3.7; extra == 'dev'
Requires-Dist: pytest-asyncio>=0.21; extra == 'dev'
Requires-Dist: pytest>=7.0; extra == 'dev'
Requires-Dist: ruff>=0.1; extra == 'dev'
Provides-Extra: postgres
Requires-Dist: asyncpg>=0.29; extra == 'postgres'
